sniffcell/__init__.py
sniffcell/main.py
sniffcell/parse_args.py
sniffcell/anno/__init__.py
sniffcell/anno/anno.py
sniffcell/anno/filter_bed_based_on_variants.py
sniffcell/anno/kmeans.py
sniffcell/anno/methyl_matrix.py
sniffcell/anno/variant_assignment.py
sniffcell/anno/vcf_to_df.py
sniffcell/deconv/__init__.py
sniffcell/deconv/deconv.py
sniffcell/dmsv/__init__.py
sniffcell/dmsv/dmsv.py
sniffcell/dmsv/statistical_test_around_sv.py
sniffcell/dmsv/sv_methylation.py
sniffcell/find/__init__.py
sniffcell/find/ctdmr.py
sniffcell/find/find.py
sniffcell-0.5.4.dist-info/licenses/LICENSE
sniffcell-0.5.4.dist-info/METADATA
sniffcell-0.5.4.dist-info/WHEEL
sniffcell-0.5.4.dist-info/entry_points.txt
sniffcell-0.5.4.dist-info/top_level.txt
sniffcell-0.5.4.dist-info/RECORD
