Metadata-Version: 2.4
Name: sniffcell
Version: 0.5.4
Summary: SniffCell: Annotate SVs cell type based on CpG methylation
Home-page: https://github.com/Fu-Yilei/SniffCell
Author: Yilei Fu
Author-email: yilei.fu@bcm.edu
License: MIT
Project-URL: Bug Tracker, https://github.com/Fu-Yilei/SniffCell/issues
Classifier: Programming Language :: Python :: 3
Classifier: License :: OSI Approved :: MIT License
Classifier: Operating System :: OS Independent
Requires-Python: >=3.10
License-File: LICENSE
Requires-Dist: pysam>=0.21.0
Requires-Dist: edlib>=1.3.9
Requires-Dist: psutil>=5.9.4
Requires-Dist: numpy>=2.2.0
Requires-Dist: pandas>=2.3.0
Requires-Dist: scipy
Requires-Dist: tqdm
Requires-Dist: scikit-learn
Dynamic: author
Dynamic: author-email
Dynamic: description
Dynamic: description-content-type
Dynamic: home-page
Dynamic: license
Dynamic: license-file
Dynamic: summary
